pykep-2.5.dist-info/top_level.txt
pykep-2.5.dist-info/RECORD
pykep-2.5.dist-info/METADATA
pykep-2.5.dist-info/WHEEL
pykep/test.py
pykep/__init__.py
pykep/.libs/libboost_serialization-a2bbf0df.so.1.70.0
pykep/.libs/libkeplerian_toolbox-9d7db9b9.so.1.0
pykep/.libs/libboost_date_time-7aa59bac.so.1.70.0
pykep/.libs/libboost_python37-8668675a.so.1.70.0
pykep/examples/_ex4.py
pykep/examples/_ex5.py
pykep/examples/_ex1.py
pykep/examples/_ex_utilities.py
pykep/examples/_ex2.py
pykep/examples/_ex8.py
pykep/examples/_ex6.py
pykep/examples/_ex9.py
pykep/examples/_ex3.py
pykep/examples/_ex10.py
pykep/examples/__init__.py
pykep/examples/_ex7.py
pykep/examples/_ex11.py
pykep/pontryagin/_leg.py
pykep/pontryagin/__init__.py
pykep/pontryagin/_dynamics.py
pykep/orbit_plots/_plots.py
pykep/orbit_plots/__init__.py
pykep/planet/planet.so
pykep/planet/__init__.py
pykep/util/load_gravity_model.py
pykep/util/util.so
pykep/util/__init__.py
pykep/util/gravity_spherical_harmonic.py
pykep/trajopt/_mr_lt_nep.py
pykep/trajopt/_mga_1dsm.py
pykep/trajopt/_pl2pl_N_impulses.py
pykep/trajopt/_mga_lt_nep.py
pykep/trajopt/_mga.py
pykep/trajopt/_direct.py
pykep/trajopt/_lt_margo.py
pykep/trajopt/_indirect.py
pykep/trajopt/_launchers.py
pykep/trajopt/__init__.py
pykep/trajopt/gym/_tandem.py
pykep/trajopt/gym/_emNimp.py
pykep/trajopt/gym/_rosetta.py
pykep/trajopt/gym/_eve_mga1dsm.py
pykep/trajopt/gym/_cassini1.py
pykep/trajopt/gym/_messenger.py
pykep/trajopt/gym/_cassini2.py
pykep/trajopt/gym/__init__.py
pykep/trajopt/gym/_juice.py
pykep/sims_flanagan/sims_flanagan.so
pykep/sims_flanagan/__init__.py
pykep/core/core.so
pykep/core/__init__.py
pykep/phasing/_knn.py
pykep/phasing/_dbscan.py
pykep/phasing/_lambert.py
pykep/phasing/__init__.py
