Metadata-Version: 2.1
Name: pykep
Version: 2.5
Summary: Basic space flight mechanics computations mostly based on perturbed Keplerian dynamics
Home-page: https://github.com/esa/pykep
Author: Dario Izzo
Author-email: dario.izzo@gmail.com
License: GPLv3+/LGPL3+
Keywords: space keplerian math physics interplanetary
Platform: Unix
Platform: Windows
Platform: OSX
Classifier: Development Status :: 4 - Beta
Classifier: Operating System :: OS Independent
Classifier: Intended Audience :: Science/Research
Classifier: Topic :: Scientific/Engineering
Classifier: Topic :: Scientific/Engineering :: Astronomy
Classifier: Topic :: Scientific/Engineering :: Mathematics
Classifier: Topic :: Scientific/Engineering :: Physics
Classifier: License :: OSI Approved :: GNU General Public License v3 or later (GPLv3+)
Classifier: License :: OSI Approved :: GNU Lesser General Public License v3 or later (LGPLv3+)
Classifier: Programming Language :: Python :: 2
Classifier: Programming Language :: Python :: 3
Requires-Dist: numpy
Requires-Dist: scipy
Requires-Dist: matplotlib
